pywttr/__init__.py
pywttr/_wttr.py
pywttr/py.typed
pywttr-4.0.1.dist-info/METADATA
pywttr-4.0.1.dist-info/WHEEL
pywttr-4.0.1.dist-info/licenses/LICENSE
pywttr-4.0.1.dist-info/RECORD
