Metadata-Version: 2.4
Name: pywttr
Version: 4.0.1
Summary: Wrapper for wttr.in weather API
Project-URL: documentation, https://pywttr.readthedocs.io
Project-URL: repository, https://github.com/monosans/pywttr
Author-email: monosans <hsyqixco@protonmail.com>
License-Expression: MIT
License-File: LICENSE
Keywords: forecast
Classifier: Framework :: Pydantic
Classifier: Framework :: Pydantic :: 2
Classifier: Natural Language :: English
Classifier: Operating System :: OS Independent
Classifier: Programming Language :: Python
Classifier: Programming Language :: Python :: 3 :: Only
Classifier: Programming Language :: Python :: 3.9
Classifier: Programming Language :: Python :: 3.10
Classifier: Programming Language :: Python :: 3.11
Classifier: Programming Language :: Python :: 3.12
Classifier: Programming Language :: Python :: 3.13
Classifier: Programming Language :: Python :: 3.14
Classifier: Programming Language :: Python :: 3.15
Classifier: Typing :: Typed
Requires-Python: >=3.9
Requires-Dist: httpx
Requires-Dist: pywttr-models<3,>=2
Requires-Dist: typing-extensions>=4
